wordsearchutils/__init__.py
wordsearchutils-1.0.1.dist-info/LICENSE
wordsearchutils-1.0.1.dist-info/METADATA
wordsearchutils-1.0.1.dist-info/WHEEL
wordsearchutils-1.0.1.dist-info/top_level.txt
wordsearchutils-1.0.1.dist-info/RECORD
