Metadata-Version: 2.1
Name: wordsearchutils
Version: 1.0.1
Summary: A library to solve word searches.
Home-page: https://github.com/TheWeirdSquid/wordsearchutils
Author: David Bootle
Author-email: davidtbootle@gmail.com
License: UNKNOWN
Platform: UNKNOWN
Classifier: Programming Language :: Python :: 3
Classifier: License :: OSI Approved :: MIT License
Classifier: Operating System :: OS Independent
Requires-Python: >=3.6
